sample/__init__.py
sample/hello.py
jpypiwa-0.0.1.dist-info/METADATA
jpypiwa-0.0.1.dist-info/WHEEL
jpypiwa-0.0.1.dist-info/top_level.txt
jpypiwa-0.0.1.dist-info/RECORD
