Metadata-Version: 2.1
Name: jpypiwa
Version: 0.0.1
Summary: Jfrog test Pypi PACKAGE
Author: Waseem
Author-email: <ncwaseem@gmail.com>
Keywords: python
Classifier: Development Status :: 1 - Planning
Classifier: Intended Audience :: Developers
Classifier: Programming Language :: Python :: 3
Classifier: Operating System :: Unix
Classifier: Operating System :: MacOS :: MacOS X
Classifier: Operating System :: Microsoft :: Windows
Requires-Dist: opencv-python
Requires-Dist: pyautogui
Requires-Dist: pyaudio
